nixcmd/__init__.py
nixcmd-0.0.1.dist-info/DESCRIPTION.rst
nixcmd-0.0.1.dist-info/METADATA
nixcmd-0.0.1.dist-info/RECORD
nixcmd-0.0.1.dist-info/WHEEL
nixcmd-0.0.1.dist-info/metadata.json
nixcmd-0.0.1.dist-info/top_level.txt
