Metadata-Version: 2.0
Name: nixcmd
Version: 0.0.1
Summary: A Python tool to get linux commands results from remote servers
Home-page: https://github.com/Adityank003/Python-useful-scripts
Author: Aditya nk
Author-email: adityank003@gmail.com
License: UNKNOWN
Platform: UNKNOWN
Classifier: Programming Language :: Python :: 2
Classifier: License :: OSI Approved :: MIT License
Classifier: Operating System :: OS Independent
